dsna_complete/__init__.py
dsna_complete/automl/__init__.py
dsna_complete/base/__ init__.py
dsna_complete-0.1.0.dist-info/METADATA
dsna_complete-0.1.0.dist-info/WHEEL
dsna_complete-0.1.0.dist-info/top_level.txt
dsna_complete-0.1.0.dist-info/RECORD
